shellscribe/__init__.py
shellscribe/shellscribe.py
shellscribe-0.2.1.dist-info/METADATA
shellscribe-0.2.1.dist-info/WHEEL
shellscribe-0.2.1.dist-info/entry_points.txt
shellscribe-0.2.1.dist-info/top_level.txt
shellscribe-0.2.1.dist-info/RECORD
